pimento/__init__.py
pimento-0.7.1.dist-info/DESCRIPTION.rst
pimento-0.7.1.dist-info/entry_points.txt
pimento-0.7.1.dist-info/METADATA
pimento-0.7.1.dist-info/metadata.json
pimento-0.7.1.dist-info/pbr.json
pimento-0.7.1.dist-info/RECORD
pimento-0.7.1.dist-info/top_level.txt
pimento-0.7.1.dist-info/WHEEL
