Metadata-Version: 2.0
Name: pimento
Version: 0.7.1
Summary: Simple CLI Menus
Home-page: https://github.com/toejough/pimento
Author: toejough
Author-email: toejough@gmail.com
License: MIT
Keywords: menu cli
Platform: UNKNOWN
Classifier: Development Status :: 4 - Beta
Classifier: Intended Audience :: Developers
Classifier: License :: OSI Approved :: MIT License
Classifier: Programming Language :: Python :: 2
Classifier: Programming Language :: Python :: 2.7
Classifier: Programming Language :: Python :: 3
Classifier: Programming Language :: Python :: 3.4
